api_dispatcher/__init__.py
api_dispatcher/validator.py
api_dispatcher-0.0.1.dist-info/LICENSE
api_dispatcher-0.0.1.dist-info/METADATA
api_dispatcher-0.0.1.dist-info/WHEEL
api_dispatcher-0.0.1.dist-info/top_level.txt
api_dispatcher-0.0.1.dist-info/RECORD
