Metadata-Version: 2.1
Name: api-dispatcher
Version: 0.0.1
Summary: This a provider to DLab that adds AWS support.
Home-page: http://dlab.apache.org/
Author: Apache Software Foundation
Author-email: dev@dlab.apache.org
License: UNKNOWN
Platform: UNKNOWN
